[
  {
    "condition": "minecraft:alternative",
    "terms": [
      {
        "condition": "minecraft:entity_properties",
        "entity": "this",
        "predicate": {
          "location": {
            "biome": "minecraft:snowy_slopes"
          }
        }
      },
      {
        "condition": "minecraft:entity_properties",
        "entity": "this",
        "predicate": {
          "location": {
            "biome": "minecraft:snowy_plains"
          }
        }
      },
      {
        "condition": "minecraft:entity_properties",
        "entity": "this",
        "predicate": {
          "location": {
            "biome": "minecraft:deep_cold_ocean"
          }
        }
      },
      {
        "condition": "minecraft:entity_properties",
        "entity": "this",
        "predicate": {
          "location": {
            "biome": "minecraft:cold_ocean"
          }
        }
      },
      {
        "condition": "minecraft:entity_properties",
        "entity": "this",
        "predicate": {
          "location": {
            "biome": "minecraft:frozen_river"
          }
        }
      },
      {
        "condition": "minecraft:entity_properties",
        "entity": "this",
        "predicate": {
          "location": {
            "biome": "minecraft:snowy_beach"
          }
        }
      },
      {
        "condition": "minecraft:entity_properties",
        "entity": "this",
        "predicate": {
          "location": {
            "biome": "minecraft:windswept_gravelly_hills"
          }
        }
      }
    ]
  }
]
